{
  "template_name": "Installation Lave-Vaisselle",
  "template_type": "quote",
  "category": "Kitchen",
  "line_items": [
    {
      "description": "Arrivée d'eau avec robinet autoperceur",
      "quantity": 1,
      "unit_price": 85.00,
      "discount_percent": 0,
      "tax_rate": 10.0
    },
    {
      "description": "Raccordement évacuation sur siphon",
      "quantity": 1,
      "unit_price": 65.00,
      "discount_percent": 0,
      "tax_rate": 10.0
    },
    {
      "description": "Prise électrique dédiée 16A",
      "quantity": 1,
      "unit_price": 95.00,
      "discount_percent": 0,
      "tax_rate": 10.0
    },
    {
      "description": "Installation et mise à niveau",
      "quantity": 1,
      "unit_price": 120.00,
      "discount_percent": 0,
      "tax_rate": 10.0
    },
    {
      "description": "Test de fonctionnement",
      "quantity": 1,
      "unit_price": 45.00,
      "discount_percent": 0,
      "tax_rate": 10.0
    }
  ],
  "terms_conditions": "Installation selon normes fabricant. Test d'étanchéité inclus. Garantie 1 an installation. TVA 10%.",
  "is_system_template": true
}
